bq.py
another_bigquery_magic-0.1.5.dist-info/licenses/LICENSE
another_bigquery_magic-0.1.5.dist-info/METADATA
another_bigquery_magic-0.1.5.dist-info/WHEEL
another_bigquery_magic-0.1.5.dist-info/top_level.txt
another_bigquery_magic-0.1.5.dist-info/RECORD
