Metadata-Version: 2.4
Name: another-bigquery-magic
Version: 0.1.5
Summary: Unofficial IPython magic command for bigquery
Author-email: Kota Mori <kmori05@gmail.com>
Project-URL: Homepage, https://github.com/kota7/another-bigquery-magic
Project-URL: Repository, https://github.com/kota7/another-bigquery-magic
Project-URL: Issues, https://github.com/kota7/another-bigquery-magic/issues
Classifier: Development Status :: 4 - Beta
Classifier: Intended Audience :: Developers
Classifier: License :: OSI Approved :: MIT License
Classifier: Programming Language :: Python :: 3
Classifier: Programming Language :: Python :: 3.7
Classifier: Programming Language :: Python :: 3.8
Classifier: Programming Language :: Python :: 3.9
Classifier: Programming Language :: Python :: 3.10
Classifier: Programming Language :: Python :: 3.11
Classifier: Programming Language :: Python :: 3.12
Requires-Python: >=3.7
License-File: LICENSE
Requires-Dist: pandas
Requires-Dist: IPython
Requires-Dist: traitlets
Requires-Dist: google-cloud-bigquery
Provides-Extra: polars
Requires-Dist: polars; extra == "polars"
Dynamic: license-file
